sinaraX
