Metadata-Version: 2.1
Name: sinaraX
Version: 1.0.2
Summary: sinaraX - TUI for sinaraml cli
Home-page: https://github.com/MiXaiLL76/sinaraX
Author: MiXaiLL76
Author-email: mike.milos@yandex.ru
Classifier: License :: OSI Approved :: Apache Software License
Classifier: Operating System :: OS Independent
Classifier: Programming Language :: Python :: 3.6
Classifier: Programming Language :: Python :: 3.7
Classifier: Programming Language :: Python :: 3.8
Classifier: Programming Language :: Python :: 3.9
Classifier: Programming Language :: Python :: 3.10
Classifier: Programming Language :: Python :: 3.11
Classifier: Programming Language :: Python :: 3.12
Classifier: Programming Language :: Python :: Implementation :: CPython
Classifier: Topic :: Scientific/Engineering :: Artificial Intelligence
Requires-Python: >=3.6
License-File: LICENSE
Requires-Dist: textual
Requires-Dist: sinaraml
